{
  "hero": "https://aokh8l4hrkrnedl2.public.blob.vercel-storage.com/suitconcern/hero/hero.jpg",
  "about": "https://aokh8l4hrkrnedl2.public.blob.vercel-storage.com/suitconcern/hero/about.jpg",
  "overons": "https://aokh8l4hrkrnedl2.public.blob.vercel-storage.com/suitconcern/hero/overons.jpg",
  "voorraad": "https://aokh8l4hrkrnedl2.public.blob.vercel-storage.com/suitconcern/hero/voorraad.jpg",
  "privatelabel": "https://aokh8l4hrkrnedl2.public.blob.vercel-storage.com/suitconcern/hero/privatelabel.jpg"
}
